AUTHORS.rst
HISTORY.rst
LICENSE
MANIFEST.in
README.rst
setup.py
gh/__init__.py
gh/base.py
gh/compat.py
gh/main.py
gh/util.py
gh/commands/__init__.py
gh/commands/follow.py
gh/commands/fork.py
gh/commands/gists.py
gh/commands/help.py
gh/commands/issues.py
gh/commands/my.py
gh/commands/pulls.py
gh/commands/repos.py
gh/commands/unfollow.py
gh_cli.egg-info/PKG-INFO
gh_cli.egg-info/SOURCES.txt
gh_cli.egg-info/dependency_links.txt
gh_cli.egg-info/entry_points.txt
gh_cli.egg-info/requires.txt
gh_cli.egg-info/top_level.txt